README.rst
setup.py
xmldict_translate/__init__.py
xmldict_translate/xmldict_translate.py
xmldict_translate.egg-info/PKG-INFO
xmldict_translate.egg-info/SOURCES.txt
xmldict_translate.egg-info/dependency_links.txt
xmldict_translate.egg-info/top_level.txt