Metadata-Version: 1.0
Name: xmldict-translate
Version: 0.1.3
Summary: UNKNOWN
Home-page: UNKNOWN
Author: Dmitriy Shikhalev
Author-email: dmitriy.shikhalev@gmail.com
License: UNKNOWN
Platform: UNKNOWN
